df_preprocessor/__init__.py
df_preprocessor/masterfile_df_preprocessor.py
df_preprocessor-1.1.dist-info/METADATA
df_preprocessor-1.1.dist-info/WHEEL
df_preprocessor-1.1.dist-info/top_level.txt
df_preprocessor-1.1.dist-info/RECORD
