Metadata-Version: 2.1
Name: df-preprocessor
Version: 1.1
Summary: library for pre-processingtools to apply on dataframes
Author: Alix C., Claeys S., Herremy J.
Author-email: 
License: UNKNOWN
Platform: UNKNOWN
Classifier: Intended Audience :: Other Audience
Classifier: Programming Language :: Python
Classifier: Programming Language :: Python :: 3.9
Classifier: Operating System :: OS Independent
Requires-Dist: pandas
Requires-Dist: plyer
Requires-Dist: numpy
